setup.py
distribution_class_Gaussian_Binomial_07292020/Binomialdistribution.py
distribution_class_Gaussian_Binomial_07292020/Gaussiandistribution.py
distribution_class_Gaussian_Binomial_07292020/Generaldistribution.py
distribution_class_Gaussian_Binomial_07292020/__init__.py
distribution_class_Gaussian_Binomial_07292020.egg-info/PKG-INFO
distribution_class_Gaussian_Binomial_07292020.egg-info/SOURCES.txt
distribution_class_Gaussian_Binomial_07292020.egg-info/dependency_links.txt
distribution_class_Gaussian_Binomial_07292020.egg-info/not-zip-safe
distribution_class_Gaussian_Binomial_07292020.egg-info/top_level.txt