Metadata-Version: 1.0
Name: distribution-class-Gaussian-Binomial-07292020
Version: 1.0
Summary: Gaussian and Binomial Distributions
Home-page: UNKNOWN
Author: UNKNOWN
Author-email: UNKNOWN
License: UNKNOWN
Platform: UNKNOWN
